[
    {
        "05-12-2021": [
            {
                "Bookingdate": "5-12-2021 09:00:00",
                "EmpID": "emp01",
                "Meeting Date": "05-12-2021 10:00:00",
                "MHour": "2"
            },
            {
                "Bookingdate": "05-12-2021 09:30:00",
                "EmpID": "emp02",
                "Meeting Date": "05-12-2021 11:00:00",
                "MHour": "2"
            },
            {
                "Bookingdate": "05-12-2021 09:00:00",
                "EmpID": "emp03",
                "Meeting Date": "05-12-2021 14:00:00",
                "MHour": "3"
            }
        ]
    },
    {
        "06-12-2021": [
            {
                "Bookingdate": "05-12-2021 09:00:0",
                "EmpID": "emp03",
                "Meeting Date": "06-12-2021 10:00:00",
                "MHour": "2"
            }
        ]
    },
    {
        "04-12-2021": [
            {
                "Bookingdate": "04-12-2021 09:00:00",
                "EmpID": "emp01",
                "Meeting Date": "04-12-2021 10:00:00",
                "MHour": "2"
            }
        ]
    }
]